psygnal/__init__.py
psygnal/_dataclass_utils.py
psygnal/_evented_decorator.py
psygnal/_evented_model.py
psygnal/_exceptions.py
psygnal/_group.py
psygnal/_group_descriptor.py
psygnal/_mypyc.py
psygnal/_queue.py
psygnal/_signal.py
psygnal/_throttler.py
psygnal/_throttler.pyi
psygnal/_weak_callback.py
psygnal/py.typed
psygnal/qt.py
psygnal/utils.py
psygnal/_pyinstaller_util/__init__.py
psygnal/_pyinstaller_util/_pyinstaller_hook.py
psygnal/_pyinstaller_util/hook-psygnal.py
psygnal/containers/__init__.py
psygnal/containers/_evented_dict.py
psygnal/containers/_evented_list.py
psygnal/containers/_evented_proxy.py
psygnal/containers/_evented_set.py
psygnal/containers/_selectable_evented_list.py
psygnal/containers/_selection.py
psygnal-0.10.2.dist-info/METADATA
psygnal-0.10.2.dist-info/WHEEL
psygnal-0.10.2.dist-info/entry_points.txt
psygnal-0.10.2.dist-info/licenses/LICENSE
psygnal-0.10.2.dist-info/RECORD
