Metadata-Version: 2.1
Name: psygnal
Version: 0.10.2
Summary: Fast python callback/event system modeled after Qt Signals
Project-URL: homepage, https://github.com/pyapp-kit/psygnal
Project-URL: repository, https://github.com/pyapp-kit/psygnal
Project-URL: documentation, https://psygnal.readthedocs.io
Author-email: Talley Lambert <talley.lambert@gmail.com>
License: BSD 3-Clause License
License-File: LICENSE
Classifier: Development Status :: 4 - Beta
Classifier: License :: OSI Approved :: BSD License
Classifier: Natural Language :: English
Classifier: Programming Language :: Python :: 3
Classifier: Programming Language :: Python :: 3.8
Classifier: Programming Language :: Python :: 3.9
Classifier: Programming Language :: Python :: 3.10
Classifier: Programming Language :: Python :: 3.11
Classifier: Programming Language :: Python :: 3.12
Classifier: Typing :: Typed
Requires-Python: >=3.8
Provides-Extra: dev
Requires-Dist: ipython; extra == 'dev'
Requires-Dist: mypy; extra == 'dev'
Requires-Dist: mypy-extensions; extra == 'dev'
Requires-Dist: pre-commit; extra == 'dev'
Requires-Dist: pyqt5; extra == 'dev'
Requires-Dist: pytest-mypy-plugins; extra == 'dev'
Requires-Dist: rich; extra == 'dev'
Requires-Dist: ruff; extra == 'dev'
Requires-Dist: typing-extensions; extra == 'dev'
Provides-Extra: docs
Requires-Dist: griffe==0.25.5; extra == 'docs'
Requires-Dist: mkdocs-material==8.5.10; extra == 'docs'
Requires-Dist: mkdocs-minify-plugin; extra == 'docs'
Requires-Dist: mkdocs-spellcheck[all]; extra == 'docs'
Requires-Dist: mkdocs==1.4.2; extra == 'docs'
Requires-Dist: mkdocstrings-python==0.8.3; extra == 'docs'
Requires-Dist: mkdocstrings==0.20.0; extra == 'docs'
Provides-Extra: proxy
Requires-Dist: wrapt; extra == 'proxy'
Provides-Extra: pydantic
Requires-Dist: pydantic; extra == 'pydantic'
Provides-Extra: test
Requires-Dist: attrs; extra == 'test'
Requires-Dist: dask; extra == 'test'
Requires-Dist: msgspec; extra == 'test'
Requires-Dist: numpy; extra == 'test'
Requires-Dist: pydantic; extra == 'test'
Requires-Dist: pyinstaller>=4.0; extra == 'test'
Requires-Dist: pytest-cov; extra == 'test'
Requires-Dist: pytest>=6.0; extra == 'test'
Requires-Dist: toolz; extra == 'test'
Requires-Dist: wrapt; extra == 'test'
Provides-Extra: testqt
Requires-Dist: pytest-qt; extra == 'testqt'
Requires-Dist: qtpy; extra == 'testqt'
